pyrebase/__init__.py
pyrebase/constants.py
pyrebase/pyrebase.py
Pirebase-3.1.29.dist-info/METADATA
Pirebase-3.1.29.dist-info/WHEEL
Pirebase-3.1.29.dist-info/top_level.txt
Pirebase-3.1.29.dist-info/RECORD
