Metadata-Version: 1.1
Name: Pirebase
Version: 3.1.29
Summary: A simple python wrapper for the Firebase API
Home-page: https://github.com/josewails/Pirebase
Author: Joseph Gitonga Wagura
Author-email: UNKNOWN
License: MIT
Keywords: Firebase
Platform: UNKNOWN
Classifier: Development Status :: 3 - Alpha
Classifier: Intended Audience :: Developers
Classifier: License :: OSI Approved :: MIT License
Classifier: Programming Language :: Python :: 3.8
